kibitzr/__init__.py
kibitzr/__main__.py
kibitzr/app.py
kibitzr/bash.py
kibitzr/bootstrap.py
kibitzr/checker.py
kibitzr/cli.py
kibitzr/compat.py
kibitzr/conf.py
kibitzr/exceptions.py
kibitzr/stash.py
kibitzr/storage.py
kibitzr/timeline.py
kibitzr/utils.py
kibitzr/fetcher/__init__.py
kibitzr/fetcher/base.py
kibitzr/fetcher/factory.py
kibitzr/fetcher/loader.py
kibitzr/fetcher/script.py
kibitzr/fetcher/simple.py
kibitzr/fetcher/browser/__init__.py
kibitzr/fetcher/browser/fetcher.py
kibitzr/fetcher/browser/launcher.py
kibitzr/fetcher/browser/trigger.py
kibitzr/notifier/__init__.py
kibitzr/notifier/bash.py
kibitzr/notifier/custom.py
kibitzr/notifier/discord.py
kibitzr/notifier/factory.py
kibitzr/notifier/gitter.py
kibitzr/notifier/gotify.py
kibitzr/notifier/mailgun.py
kibitzr/notifier/ntfy.py
kibitzr/notifier/slack.py
kibitzr/notifier/smtp.py
kibitzr/notifier/stash.py
kibitzr/notifier/telegram.py
kibitzr/notifier/twilio.py
kibitzr/notifier/webhook.py
kibitzr/notifier/zapier.py
kibitzr/transformer/__init__.py
kibitzr/transformer/factory.py
kibitzr/transformer/html.py
kibitzr/transformer/jinja_transform.py
kibitzr/transformer/json_transforms.py
kibitzr/transformer/plain_text.py
kibitzr/transformer/utils.py
kibitzr/transformer/xpath.py
kibitzr-8.0.0.dist-info/AUTHORS.rst
kibitzr-8.0.0.dist-info/LICENSE
kibitzr-8.0.0.dist-info/METADATA
kibitzr-8.0.0.dist-info/WHEEL
kibitzr-8.0.0.dist-info/entry_points.txt
kibitzr-8.0.0.dist-info/top_level.txt
kibitzr-8.0.0.dist-info/RECORD
