Metadata-Version: 2.1
Name: kibitzr
Version: 8.0.0
Summary: Self hosted web page changes monitoring
Home-page: https://github.com/kibitzr/kibitzr
Author: Peter Demin
Author-email: kibitzrrr@gmail.com
License: MIT license
Keywords: kibitzr
Classifier: Development Status :: 6 - Mature
Classifier: Intended Audience :: Developers
Classifier: License :: OSI Approved :: MIT License
Classifier: Natural Language :: English
Classifier: Programming Language :: Python :: 3.9
Classifier: Programming Language :: Python :: 3.10
Classifier: Programming Language :: Python :: 3.11
Classifier: Programming Language :: Python :: 3.12
Classifier: Programming Language :: Python :: 3.13
Requires-Python: >=3.9
License-File: LICENSE
License-File: AUTHORS.rst
Requires-Dist: click
Requires-Dist: Jinja2
Requires-Dist: bs4
Requires-Dist: cachecontrol
Requires-Dist: defusedxml
Requires-Dist: entrypoints
Requires-Dist: lazy-object-proxy
Requires-Dist: lxml
Requires-Dist: python-telegram-bot
Requires-Dist: pytimeparse
Requires-Dist: pyyaml
Requires-Dist: requests
Requires-Dist: schedule
Requires-Dist: selenium
Requires-Dist: six
Requires-Dist: psutil
Requires-Dist: twilio
Requires-Dist: sh<2
Provides-Extra: locked
Requires-Dist: aiohappyeyeballs==2.6.1; extra == "locked"
Requires-Dist: aiohttp==3.11.18; extra == "locked"
Requires-Dist: aiohttp-retry==2.9.1; extra == "locked"
Requires-Dist: aiosignal==1.3.2; extra == "locked"
Requires-Dist: anyio==4.9.0; extra == "locked"
Requires-Dist: async-timeout==5.0.1; extra == "locked"
Requires-Dist: attrs==25.3.0; extra == "locked"
Requires-Dist: beautifulsoup4==4.13.4; extra == "locked"
Requires-Dist: bs4==0.0.2; extra == "locked"
Requires-Dist: cachecontrol==0.14.3; extra == "locked"
Requires-Dist: certifi==2025.4.26; extra == "locked"
Requires-Dist: charset-normalizer==3.4.2; extra == "locked"
Requires-Dist: click==8.1.8; extra == "locked"
Requires-Dist: defusedxml==0.7.1; extra == "locked"
Requires-Dist: entrypoints==0.4; extra == "locked"
Requires-Dist: exceptiongroup==1.2.2; extra == "locked"
Requires-Dist: frozenlist==1.6.0; extra == "locked"
Requires-Dist: h11==0.16.0; extra == "locked"
Requires-Dist: httpcore==1.0.9; extra == "locked"
Requires-Dist: httpx==0.28.1; extra == "locked"
Requires-Dist: idna==3.10; extra == "locked"
Requires-Dist: jinja2==3.1.6; extra == "locked"
Requires-Dist: lazy-object-proxy==1.11.0; extra == "locked"
Requires-Dist: lxml==5.4.0; extra == "locked"
Requires-Dist: markupsafe==3.0.2; extra == "locked"
Requires-Dist: msgpack==1.1.0; extra == "locked"
Requires-Dist: multidict==6.4.3; extra == "locked"
Requires-Dist: outcome==1.3.0.post0; extra == "locked"
Requires-Dist: propcache==0.3.1; extra == "locked"
Requires-Dist: psutil==7.0.0; extra == "locked"
Requires-Dist: pyjwt==2.10.1; extra == "locked"
Requires-Dist: pysocks==1.7.1; extra == "locked"
Requires-Dist: python-telegram-bot==22.0; extra == "locked"
Requires-Dist: pytimeparse==1.1.8; extra == "locked"
Requires-Dist: pyyaml==6.0.2; extra == "locked"
Requires-Dist: requests==2.32.3; extra == "locked"
Requires-Dist: schedule==1.2.2; extra == "locked"
Requires-Dist: selenium==4.32.0; extra == "locked"
Requires-Dist: six==1.17.0; extra == "locked"
Requires-Dist: sniffio==1.3.1; extra == "locked"
Requires-Dist: sortedcontainers==2.4.0; extra == "locked"
Requires-Dist: soupsieve==2.7; extra == "locked"
Requires-Dist: trio==0.30.0; extra == "locked"
Requires-Dist: trio-websocket==0.12.2; extra == "locked"
Requires-Dist: twilio==9.6.0; extra == "locked"
Requires-Dist: typing-extensions==4.13.2; extra == "locked"
Requires-Dist: urllib3[socks]==2.4.0; extra == "locked"
Requires-Dist: websocket-client==1.8.0; extra == "locked"
Requires-Dist: wsproto==1.2.0; extra == "locked"
Requires-Dist: yarl==1.20.0; extra == "locked"
Requires-Dist: sh<2; extra == "locked"
